ListenerCLI/__init__.py
ListenerCLI/cli.py
listenercli-0.1.0.dist-info/licenses/LICENSE
listenercli-0.1.0.dist-info/METADATA
listenercli-0.1.0.dist-info/WHEEL
listenercli-0.1.0.dist-info/entry_points.txt
listenercli-0.1.0.dist-info/top_level.txt
listenercli-0.1.0.dist-info/RECORD
