Metadata-Version: 2.4
Name: listenercli
Version: 0.1.0
Summary: Private CLI based speech-to-text tool
License-Expression: MIT
Classifier: Programming Language :: Python :: 3
Classifier: Operating System :: OS Independent
Requires-Python: >=3.13
License-File: LICENSE
Requires-Dist: click>=8.3.1
Requires-Dist: numpy>=2.3.5
Requires-Dist: pyperclip>=1.11.0
Requires-Dist: rich>=14.2.0
Requires-Dist: sounddevice>=0.5.3
Requires-Dist: faster-whisper>=1.0.0
Dynamic: license-file
